Metadata-Version: 2.1
Name: getbooru
Version: 1.0.0
Summary: Python Wrapper For Booru Websites
Home-page: https://github.com/KuuhakuTeam/getbooru
Author: fnixdev
Author-email: luisgatn000@gmail.com
License: MIT
Keywords: Gelbooru,Safebooru
Platform: UNKNOWN
Classifier: Programming Language :: Python :: 3
Classifier: Programming Language :: Python :: 3.7
Classifier: Programming Language :: Python :: 3.8
Classifier: Programming Language :: Python :: 3.9
Classifier: Programming Language :: Python :: 3.10
Classifier: Development Status :: 5 - Production/Stable
Classifier: License :: OSI Approved :: MIT License
Classifier: Operating System :: OS Independent
Classifier: Intended Audience :: Developers
Requires-Python: >3.6, <3.11
License-File: LICENSE
